marketdataserver/__init__.py
marketdataserver/client.py
marketdataserver/httpserver.py
marketdataserver/message.py
marketdataserver-0.0.2.dist-info/METADATA
marketdataserver-0.0.2.dist-info/WHEEL
marketdataserver-0.0.2.dist-info/top_level.txt
marketdataserver-0.0.2.dist-info/RECORD
