Metadata-Version: 2.1
Name: marketdataserver
Version: 0.0.2
Summary: marketdata server
Home-page: https://github.com/elephasinvestment.com/elephasdb
Author: xitongsys
Author-email: xitongsys@gmail.com
License: UNKNOWN
Platform: UNKNOWN
Requires-Dist: yaml
Requires-Dist: json
